coalition/__init__.py
coalition/coalition.py
coalition/tests.py
coalition/locale/__init__.py
coalition/locale/countries.py
coalition/vcard/__init__.py
coalition/vcard/defintions.py
coalition/vcard/utility.py
coalition/vcard/vcard.py
coalition-0.0.0.dev5.dist-info/DESCRIPTION.rst
coalition-0.0.0.dev5.dist-info/METADATA
coalition-0.0.0.dev5.dist-info/RECORD
coalition-0.0.0.dev5.dist-info/WHEEL
coalition-0.0.0.dev5.dist-info/entry_points.txt
coalition-0.0.0.dev5.dist-info/metadata.json
coalition-0.0.0.dev5.dist-info/top_level.txt
