Metadata-Version: 2.0
Name: coalition
Version: 0.0.0.dev5
Summary: A suite of office tools developed in Python.
Home-page: https://github.com/thee-engineer/coalition
Author: Alexandru-Paul Copil (thee-engineer)
Author-email: alexandru.p.copil@gmail.com
License: 4-Clause BSD License
Keywords: coalition contacts wallet passwords office business
Platform: UNKNOWN
Classifier: Development Status :: 1 - Planning
Classifier: Intended Audience :: Developers
Classifier: Intended Audience :: Customer Service
Classifier: Intended Audience :: End Users/Desktop
Classifier: Topic :: Communications :: Chat
Classifier: Topic :: Communications :: Email
Classifier: Topic :: Office/Business
Classifier: Topic :: Security
Classifier: License :: OSI Approved :: BSD License
Classifier: Natural Language :: English
Classifier: Programming Language :: Python :: 2.7
